odoo/addons/partner_helper/README.rst
odoo/addons/partner_helper/__init__.py
odoo/addons/partner_helper/__manifest__.py
odoo/addons/partner_helper/i18n/am.po
odoo/addons/partner_helper/i18n/ar.po
odoo/addons/partner_helper/i18n/bg.po
odoo/addons/partner_helper/i18n/bs.po
odoo/addons/partner_helper/i18n/ca.po
odoo/addons/partner_helper/i18n/cs.po
odoo/addons/partner_helper/i18n/cs_CZ.po
odoo/addons/partner_helper/i18n/da.po
odoo/addons/partner_helper/i18n/de.po
odoo/addons/partner_helper/i18n/el_GR.po
odoo/addons/partner_helper/i18n/en_GB.po
odoo/addons/partner_helper/i18n/es.po
odoo/addons/partner_helper/i18n/es_CR.po
odoo/addons/partner_helper/i18n/es_EC.po
odoo/addons/partner_helper/i18n/es_MX.po
odoo/addons/partner_helper/i18n/es_VE.po
odoo/addons/partner_helper/i18n/et.po
odoo/addons/partner_helper/i18n/eu.po
odoo/addons/partner_helper/i18n/fi.po
odoo/addons/partner_helper/i18n/fr.po
odoo/addons/partner_helper/i18n/fr_CA.po
odoo/addons/partner_helper/i18n/fr_CH.po
odoo/addons/partner_helper/i18n/gl.po
odoo/addons/partner_helper/i18n/hr.po
odoo/addons/partner_helper/i18n/hr_HR.po
odoo/addons/partner_helper/i18n/hu.po
odoo/addons/partner_helper/i18n/it.po
odoo/addons/partner_helper/i18n/ja.po
odoo/addons/partner_helper/i18n/lt.po
odoo/addons/partner_helper/i18n/lv.po
odoo/addons/partner_helper/i18n/mk.po
odoo/addons/partner_helper/i18n/mn.po
odoo/addons/partner_helper/i18n/nb.po
odoo/addons/partner_helper/i18n/nb_NO.po
odoo/addons/partner_helper/i18n/nl.po
odoo/addons/partner_helper/i18n/nl_BE.po
odoo/addons/partner_helper/i18n/nl_NL.po
odoo/addons/partner_helper/i18n/partner_helper.pot
odoo/addons/partner_helper/i18n/pl.po
odoo/addons/partner_helper/i18n/pt.po
odoo/addons/partner_helper/i18n/pt_BR.po
odoo/addons/partner_helper/i18n/pt_PT.po
odoo/addons/partner_helper/i18n/ro.po
odoo/addons/partner_helper/i18n/ru.po
odoo/addons/partner_helper/i18n/sk.po
odoo/addons/partner_helper/i18n/sl.po
odoo/addons/partner_helper/i18n/sr@latin.po
odoo12_addon_partner_helper-12.0.0.1.0.99.dev9.dist-info/METADATA
odoo12_addon_partner_helper-12.0.0.1.0.99.dev9.dist-info/WHEEL
odoo12_addon_partner_helper-12.0.0.1.0.99.dev9.dist-info/top_level.txt
odoo12_addon_partner_helper-12.0.0.1.0.99.dev9.dist-info/RECORD
